wakati/__init__.py
wakati/wakati.py
wakati-1.1.dist-info/DESCRIPTION.rst
wakati-1.1.dist-info/METADATA
wakati-1.1.dist-info/RECORD
wakati-1.1.dist-info/WHEEL
wakati-1.1.dist-info/metadata.json
wakati-1.1.dist-info/top_level.txt
