Metadata-Version: 2.0
Name: wakati
Version: 1.1
Summary: Easy timing in Python modules
Home-page: https://github.com/DHI-GRAS/wakati
Author: Dion Häfner
Author-email: dimh@dhigroup.com
License: UNKNOWN
